nwalign3/cnwalign.c
nwalign3/nwserver.py
nwalign3/wrappers.py
nwalign3/cnwalign.cpython-37m-x86_64-linux-gnu.so
nwalign3/__init__.py
nwalign3/matrices/BLOSUM62
nwalign3/matrices/PAM250
nwalign3/matrices/__init__.py
nwalign3-0.1.5.dist-info/WHEEL
nwalign3-0.1.5.dist-info/top_level.txt
nwalign3-0.1.5.dist-info/METADATA
nwalign3-0.1.5.dist-info/RECORD
nwalign3-0.1.5.dist-info/entry_points.txt
